nse_calendar/__init__.py
nse_calendar/calendar.py
nse_calendar/data/trading_days.xlsx
nse_trading_calendar-0.1.6.dist-info/METADATA
nse_trading_calendar-0.1.6.dist-info/WHEEL
nse_trading_calendar-0.1.6.dist-info/top_level.txt
nse_trading_calendar-0.1.6.dist-info/RECORD
