Metadata-Version: 2.4
Name: nse-trading-calendar
Version: 0.1.6
Summary: Check NSE trading days and type using historical data.
Home-page: https://github.com/yourusername/nse-trading-calendar
Author: Naveen Gupta
Author-email: naveeng1520@gmail.com
License: MIT
Classifier: Programming Language :: Python :: 3
Classifier: License :: OSI Approved :: MIT License
Classifier: Operating System :: OS Independent
Requires-Python: >=3.6
Requires-Dist: pandas
Requires-Dist: openpyxl
Dynamic: author
Dynamic: author-email
Dynamic: classifier
Dynamic: description
Dynamic: description-content-type
Dynamic: home-page
Dynamic: license
Dynamic: requires-dist
Dynamic: requires-python
Dynamic: summary
